<odoo>
  <data>
      <record id="mail_activity_inherit_form_view" model="ir.ui.view">
			<field name="name">Mail Activity Inherit form View</field>
			<field name="model">mail.activity</field>
			<field name="inherit_id" ref="mail.mail_activity_view_form_popup"/>
			<field name="arch" type="xml">
                <xpath expr="//field[@name='date_deadline']" position="attributes">
					 <attribute name="invisible">1</attribute>
				</xpath>
                <xpath expr="//field[@name='date_deadline']" position="after">
                    <field name="date_due"/>
<!--                    <label for="interval_number" invisible="1"/>-->
<!--					<div class="o_row" invisible="1">-->
<!--						<field name="interval_type" class="oe_inline"/>-->
<!--						<field name="interval_number" class="oe_inline"/>-->
<!--					</div>-->
<!--                    <field name="sh_date_deadline"  invisible="1"/>-->
                </xpath>
            </field>
      </record>
  </data>
</odoo>